hy_ipython/__init__.py
hy_ipython/magic.py
hy_ipython-0.0.1.post2.dist-info/LICENSE.txt
hy_ipython-0.0.1.post2.dist-info/WHEEL
hy_ipython-0.0.1.post2.dist-info/METADATA
hy_ipython-0.0.1.post2.dist-info/RECORD
