Metadata-Version: 2.1
Name: hy-ipython
Version: 0.0.1.post2
Summary: Evaluate Hy code cells using %hy and %%hy magics.
Author-email: Gregory Werbin <outthere@me.gregwerbin.com>
Classifier: Framework :: IPython
Classifier: Framework :: Jupyter
Classifier: Intended Audience :: Developers
Classifier: License :: OSI Approved
Classifier: Operating System :: OS Independent
Classifier: Programming Language :: Lisp
Classifier: Programming Language :: Scheme
Classifier: Programming Language :: Python
Classifier: Programming Language :: Python :: 3
Requires-Dist: hy == 0.24
Requires-Dist: ipython
Project-URL: Home, https://sr.ht/~wintershadows/hy-ipython
Project-URL: Source, https://git.sr.ht/~wintershadows/hy-ipython
